ascengine/__init__.py
ascengine/core/__init__.py
ascengine/core/display.py
ascengine/core/gameobject.py
ascengine/core/input_manager.py
ascengine/core/main.py
ascengine/core/prefs.py
ascengine/core/renderer.py
ascengine/core/sprite.py
ascengine/core/ui.py
ascengine/core/utils.py
ascengine-0.0.3.dist-info/METADATA
ascengine-0.0.3.dist-info/WHEEL
ascengine-0.0.3.dist-info/top_level.txt
ascengine-0.0.3.dist-info/RECORD
