Metadata-Version: 2.4
Name: ascengine
Version: 0.0.3
Requires-Dist: pynput
Dynamic: requires-dist
